[
  {
    "title": "Core Team",
    "members": [
      {
        "name": "Juan Manuel Baiutti",
        "photoUrl": "https://lh3.googleusercontent.com/Iaa8hB4L4JICT5d9Ct4bqX3xpsW__HLZVQC8mrRb1QyoTj-5AZkFJmPgtOml6Sa7lbqcCFknIw=w1366-h768-rw-no",
        "socials": [
          {
            "icon": "gplus",
            "link": "google.com/+JuanmaBaiutti",
            "name": "Google+"
          },
          {
            "icon": "twitter",
            "link": "@juanmab",
            "name": "Twitter"
          }
        ],
        "title": "Project Manager, Manager de GDG Buenos Aires"
      },
      {
        "name": "Yury Camacho",
        "photoUrl": "https://lh3.googleusercontent.com/-4TQM4uQuQ-c/AAAAAAAAAAI/AAAAAAAAHRQ/bkHlSlGdQhw/s120-p-rw-no/photo.jpg",
        "socials": [
          {
            "icon": "gplus",
            "link": "google.com/+YuryCamacho",
            "name": "Google+"
          },
          {
            "icon": "twitter",
            "link": "https://twitter.com/camachoyury",
            "name": "Twitter"
          }
        ],
        "title": "Mobile Technical Lead en Globant"
      },
      {
        "name": "Jorge Cano",
        "photoUrl": "https://lh3.googleusercontent.com/0iT0FOwTu-m1P3xhrFCS02ocO2PD4GlbiQvOMuZVtNeH2Fu0-xvChYnm9kwulWHiJE2P5rGykNyZrw=w5120-h3200-rw-no/photo.jpg",
        "socials": [
          {
            "icon": "gplus",
            "link": "google.com/+JorgeCanojc",
            "name": "Google+"
          },
          {
            "icon": "twitter",
            "link": "https://twitter.com/jorgeucano",
            "name": "Twitter"
          }
        ],
        "title": "Google Developer Expert: Web Technologies, Angular"
      },
      {
        "name": "Gustavo Cardelle",
        "photoUrl": "https://lh6.googleusercontent.com/-2blXIg9egdI/T70GNsiSkBI/AAAAAAAAMYI/Z2Mt-nHaEkg/s300-no/Gustavo-Cardelle-G%252B.png",
        "socials": [
          {
            "icon": "gplus",
            "link": "google.com/+GustavoCardelle",
            "name": "Google+"
          },
          {
            "icon": "twitter",
            "link": "https://www.twitter.com/gu5tavo71",
            "name": "Twitter"
          }
        ],
        "title": "Consultor IT, Manager de GDG Buenos Aires"
      },
      {
        "name": "Leonardo Condori",
        "photoUrl": "https://lh3.googleusercontent.com/OdiILrqrGjOhQRRxWFPMxfEppFww7o-vlZAH9zRmNv8T2hbmp2XHxm4ubSfFFEhcfKMrdhhApgg=w5120-h3200-rw-no/photo.jpg",
        "socials": [
          {
            "icon": "gplus",
            "link": "google.com/+LeonardoCondori",
            "name": "Google+"
          },
          {
            "icon": "twitter",
            "link": "https://twitter.com/leocondori",
            "name": "Twitter"
          }
        ],
        "title": "Periodista y Programador"
      },
      {
        "name": "Juan Irungaray",
        "photoUrl": "https://lh3.googleusercontent.com/-xB6EHqyETqc/AAAAAAAAAAI/AAAAAAAAX5U/bgaelqjOnx0/s120-p-rw-no/photo.jpg",
        "socials": [
          {
            "icon": "gplus",
            "link": "google.com/+JuanIrungaray",
            "name": "Google+"
          },
          {
            "icon": "twitter",
            "link": "https://www.twitter.com/jirungaray",
            "name": "Twitter"
          }
        ],
        "title": "Developer Relations Program Manager @ Google, Co-Founder GDG Buenos Aires"
      },
      {
        "name": "Andrés Villanueva",
        "photoUrl": "https://lh3.googleusercontent.com/-9-WqHdvM9QM/AAAAAAAAAAI/AAAAAAAAEOw/jKa4y5Lpzi0/s120-p-rw-no/photo.jpg",
        "socials": [
          {
            "icon": "gplus",
            "link": "google.com/+AndresVillanuevand",
            "name": "Google+"
          },
          {
            "icon": "twitter",
            "link": "https://twitter.com/villanuevand",
            "name": "Twitter"
          }
        ],
        "title": "Frontend Developer. ngVenezuela Community Lead &  @bairesweb Co-founder."
      },
      {
        "name": "Agustina Vemi",
        "photoUrl": "/images/people/diana_pinchuk.jpg",
        "socials": [
          {
            "icon": "gplus",
            "link": "https://plus.google.com/+DianaPinchuk",
            "name": "Google+"
          },
          {
            "icon": "facebook",
            "link": "https://www.facebook.com/diana.pinchuk.9",
            "name": "Facebook"
          }
        ],
        "title": "Social and media"
      },
      {
        "name": "Valeria Viva",
        "photoUrl": "https://lh3.googleusercontent.com/dLx2wkJQO7WW-1wdNefkfVzwHqrlYEPw_Nv_c-e9fvoA7rfzTEdja0Uo2YItWP22zyxj7fOgRA=w5120-h3200-rw-no",
        "socials": [
          {
            "icon": "gplus",
            "link": "https://plus.google.com/+ValeriaViva",
            "name": "Google+"
          },
          {
            "icon": "twitter",
            "link": "https://www.twitter.com/valeriaviva",
            "name": "Twitter"
          }
        ],
        "title": "Ingeniera, escritora, tecnóloga y emprendedora"
      }
    ]
  }
]
